BCD.v
module seg (BCD, seg);
input [3:0] BCD;
output [7:0] seg;
reg [7:0]  seg;
always @(BCD) begin
    case (BCD)
        4'h0: seg = 8'hc0;
        4'h1: seg = 8'hf9;
        4'h2: seg = 8'ha4;
        4'h3: seg = 8'hb0;
        4'h4: seg = 8'h99;
        4'h5: seg = 8'h92;
        4'h6: seg = 8'h82;
        4'h7: seg = 8'hf8;
        4'h8: seg = 8'h80;
        4'h9: seg = 8'h90;
        default: seg = 8'hff; 
    endcase
end
endmodule

module dff (clk, D, Din, load, Q4);
input clk, D, Din, load;
output reg Q4;
always@ (posedge clk)
    if (load) 
        Q4 = Din;
    else 
        Q4 = D;
endmodule

module BCD(clk, load, rst_syn, data, Q_out, seg_out);
reg Q0, Q1, Q2, Q3;
input clk, rst_syn, load;
input [3:0] data;
output [3:0] Q_out;
output [7:0]seg_out;
wire [3:0] Q_out;
wire [7:0] seg_out;

seg BCD_seg(Q_out, seg_out);
dff BCD_dff0(clk, Q0, Q0, load, Q_out[0]);
dff BCD_dff1(clk, Q1, Q1, load, Q_out[1]);
dff BCD_dff2(clk, Q2, Q2, load, Q_out[2]);
dff BCD_dff3(clk, Q3, Q3, load, Q_out[3]);

always@ (posedge clk)
begin
    if (!rst_syn)begin
        Q0=0;
        Q1=0;
        Q2=0;
        Q3=0;
    end

    else if (load)begin
        Q0<=data[0];
        Q1<=data[1];
        Q2<=data[2];
        Q3<=data[3];
    end
    
    else
        if (Q0==1 && Q3==1)begin
            Q0<=0;
            Q3<=0;   
        end
        
        else begin
            Q0 <= ~Q0;
            Q1 <= (Q0 & ~Q1) | (Q1 & ~Q0);
            Q2 <= (Q2 & ~Q1) | (Q2 & ~Q0) | (~Q2 & Q1 & Q0);
            Q3 <= Q3 | (Q0 & Q1 & Q2);
        end

    end
endmodule

BCD_tb.v
`timescale 1ns/1ps
module BCD_tb;
reg clk;
reg rst_syn;
reg load;
reg [3:0]data;
wire [7:0]seg_out;
wire [3:0]Q_out;

BCD BCD_tb(clk, load, rst_syn, data, Q_out, seg_out);

initial begin
    clk = 1;
    rst_syn = 1;
    load = 1;
    data = 4'b1000;
end

always #50 clk = ~clk;

initial #100 load = 1'b0;
initial #200 load = 1'b1;
initial #300 load = 1'b0;
initial #700 rst_syn = 1'b0;
initial #800 rst_syn = 1'b1;
initial #2000 $finish;

initial begin
    $dumpfile("BCD.vcd");
    $dumpvars(0, BCD_tb);
end
endmodule

BCD.vcd
$date
	Wed May 04 22:06:18 2022
$end
$version
	Icarus Verilog
$end
$timescale
	1ps
$end
$scope module BCD_tb $end
$scope module BCD_tb $end
$var wire 1 ! clk $end
$var wire 4 " data [3:0] $end
$var wire 1 # load $end
$var wire 1 $ rst_syn $end
$var wire 8 % seg_out [7:0] $end
$var wire 4 & Q_out [3:0] $end
$var reg 1 ' Q0 $end
$var reg 1 ( Q1 $end
$var reg 1 ) Q2 $end
$var reg 1 * Q3 $end
$scope module BCD_dff0 $end
$var wire 1 ' D $end
$var wire 1 ' Din $end
$var wire 1 ! clk $end
$var wire 1 # load $end
$var reg 1 + Q4 $end
$upscope $end
$scope module BCD_dff1 $end
$var wire 1 ( D $end
$var wire 1 ( Din $end
$var wire 1 ! clk $end
$var wire 1 # load $end
$var reg 1 , Q4 $end
$upscope $end
$scope module BCD_dff2 $end
$var wire 1 ) D $end
$var wire 1 ) Din $end
$var wire 1 ! clk $end
$var wire 1 # load $end
$var reg 1 - Q4 $end
$upscope $end
$scope module BCD_dff3 $end
$var wire 1 * D $end
$var wire 1 * Din $end
$var wire 1 ! clk $end
$var wire 1 # load $end
$var reg 1 . Q4 $end
$upscope $end
$scope module BCD_seg $end
$var wire 4 / BCD [3:0] $end
$var reg 8 0 seg [7:0] $end
$upscope $end
$upscope $end
$upscope $end
$enddefinitions $end
#0
$dumpvars
bx 0
bx /
x.
x-
x,
x+
1*
0)
0(
0'
bx &
bx %
1$
1#
b1000 "
1!
$end
#50000
0!
#100000
1'
b10000000 %
b10000000 0
1.
0-
0,
b1000 &
b1000 /
0+
1!
0#
#150000
0!
#200000
0'
b10010000 %
b10010000 0
b1001 &
b1001 /
1+
1!
1#
#250000
0!
#300000
1'
b10000000 %
b10000000 0
b1000 &
b1000 /
0+
1!
0#
#350000
0!
#400000
0*
0'
b10010000 %
b10010000 0
b1001 &
b1001 /
1+
1!
#450000
0!
#500000
1'
b11000000 %
b11000000 0
0.
b0 &
b0 /
0+
1!
#550000
0!
#600000
1(
0'
b11111001 %
b11111001 0
b1 &
b1 /
1+
1!
#650000
0!
#700000
b10100100 %
b10100100 0
0(
1,
b10 &
b10 /
0+
1!
0$
#750000
0!
#800000
1'
b11000000 %
b11000000 0
b0 &
b0 /
0,
1!
1$
#850000
0!
#900000
1(
0'
b11111001 %
b11111001 0
b1 &
b1 /
1+
1!
#950000
0!
#1000000
1'
b10100100 %
b10100100 0
0+
b10 &
b10 /
1,
1!
#1050000
0!
#1100000
1)
0(
0'
b10110000 %
b10110000 0
b11 &
b11 /
1+
1!
#1150000
0!
#1200000
1'
b10011001 %
b10011001 0
0+
0,
b100 &
b100 /
1-
1!
#1250000
0!
#1300000
1(
0'
b10010010 %
b10010010 0
b101 &
b101 /
1+
1!
#1350000
0!
#1400000
1'
b10000010 %
b10000010 0
0+
b110 &
b110 /
1,
1!
#1450000
0!
#1500000
1*
0)
0(
0'
b11111000 %
b11111000 0
b111 &
b111 /
1+
1!
#1550000
0!
#1600000
1'
b10000000 %
b10000000 0
0+
0,
0-
b1000 &
b1000 /
1.
1!
#1650000
0!
#1700000
0*
0'
b10010000 %
b10010000 0
b1001 &
b1001 /
1+
1!
#1750000
0!
#1800000
1'
b11000000 %
b11000000 0
0+
b0 &
b0 /
0.
1!
#1850000
0!
#1900000
1(
0'
b11111001 %
b11111001 0
b1 &
b1 /
1+
1!
#1950000
0!
#2000000
1'
b10100100 %
b10100100 0
0+
b10 &
b10 /
1,
1!
